Metadata-Version: 1.0
Name: calculator-test-leonardo
Version: 0.1
Summary: Simple calculator with python
Home-page: https://github.com/leonardoishii07/calculator
Author: Leonardo Ishii
Author-email: leoishii@outlook.com
License: USP
Platform: UNKNOWN
